engine/__init__.py
engine/core.py
engine/opencv.py
upgraded_engineer-0.2.1.dist-info/LICENSE
upgraded_engineer-0.2.1.dist-info/METADATA
upgraded_engineer-0.2.1.dist-info/WHEEL
upgraded_engineer-0.2.1.dist-info/top_level.txt
upgraded_engineer-0.2.1.dist-info/RECORD
