Metadata-Version: 2.1
Name: upgraded-engineer
Version: 0.2.1
Summary: Python "API" for interacting with rusty-engine
Home-page: https://github.com/opensight-cv/upgraded-engineer
Author: Caleb Xavier Berger
Author-email: caleb.x.berger@gmail.com
License: UNKNOWN
Platform: UNKNOWN
Classifier: License :: OSI Approved :: MIT License
Classifier: Intended Audience :: Developers
Classifier: Natural Language :: English
Classifier: Operating System :: OS Independent
Classifier: Programming Language :: Python :: 3
Classifier: Topic :: Multimedia :: Video
Classifier: Topic :: Software Development :: Libraries :: Python Modules
